ops/__init__.py
ops/__main__.py
ops/assets/__init__.py
ops/assets/meirg-logo.jpg
ops/core/__init__.py
ops/core/app.py
ops/utils/__init__.py
ops/utils/img_ascii.py
ops/utils/message.py
ops_utils-0.0.1.dist-info/METADATA
ops_utils-0.0.1.dist-info/WHEEL
ops_utils-0.0.1.dist-info/entry_points.txt
ops_utils-0.0.1.dist-info/top_level.txt
ops_utils-0.0.1.dist-info/RECORD
